LICENSE
MANIFEST.in
README.rst
setup.py
docs/Makefile
docs/make.bat
docs/source/changelog.rst
docs/source/conf.py
docs/source/index.rst
docs/source/topics/introduction.rst
src/pact_state_provider/__init__.py
src/pact_state_provider/example.py
src/pact_state_provider.egg-info/PKG-INFO
src/pact_state_provider.egg-info/SOURCES.txt
src/pact_state_provider.egg-info/dependency_links.txt
src/pact_state_provider.egg-info/entry_points.txt
src/pact_state_provider.egg-info/requires.txt
src/pact_state_provider.egg-info/top_level.txt