Metadata-Version: 2.1
Name: pact-state-provider
Version: 1.0.9
Summary: Simple server to provide an endpoint used by pact to generate a provider state
Home-page: https://github.com/nalch/pact-state-provider
Author: nalch
Author-email: Scholze.Kristian@gmail.com
License: Apache-2.0
Platform: UNKNOWN
Classifier: Intended Audience :: Developers
Classifier: License :: OSI Approved :: Apache Software License
Classifier: Operating System :: OS Independent
Classifier: Programming Language :: Python
Classifier: Programming Language :: Python :: 3.6
